reader/Reader.py
reader/__init__.py
reader/__main__.py
csv_reader-1.1.0.dist-info/LICENSE
csv_reader-1.1.0.dist-info/METADATA
csv_reader-1.1.0.dist-info/WHEEL
csv_reader-1.1.0.dist-info/entry_points.txt
csv_reader-1.1.0.dist-info/top_level.txt
csv_reader-1.1.0.dist-info/RECORD
