Metadata-Version: 2.1
Name: csv-reader
Version: 1.1.0
Summary: reader library for csv files.
Home-page: https://github.com/weeb-kun/csv-reader
Author: weebkun
License: Apache 2.0
Platform: UNKNOWN
